ghost/__init__.py
ghost/engine.py
ghost/npc_demo.py
ghost/step.py
ghocentric_ghost_engine-0.1.2.dist-info/METADATA
ghocentric_ghost_engine-0.1.2.dist-info/WHEEL
ghocentric_ghost_engine-0.1.2.dist-info/entry_points.txt
ghocentric_ghost_engine-0.1.2.dist-info/top_level.txt
ghocentric_ghost_engine-0.1.2.dist-info/RECORD
