Metadata-Version: 2.4
Name: ghocentric-ghost-engine
Version: 0.1.2
Summary: Ghost cognitive engine
Author: Shane Heckathorn
License: MIT
Keywords: ai,engine,cognition,simulation
Classifier: Programming Language :: Python :: 3
Classifier: Programming Language :: Python :: 3 :: Only
Classifier: License :: OSI Approved :: MIT License
Classifier: Operating System :: OS Independent
Requires-Python: >=3.9
